{
  "username": "amelie.rolland",
  "name": "Amelie Rolland",
  "generated_at": "2026-04-08T20:22:15.388369",
  "summary": {
    "message_count": 239,
    "channels_active": 7,
    "unique_people_mentioned": 7,
    "unique_mentioners": 6,
    "days_in_window": 22,
    "days_scale": 0.96
  },
  "categories": {
    "sentiment": {
      "score": 5.4,
      "pos_count": 17,
      "neg_count": 6,
      "positive_markers": [
        {
          "category": "Thanking",
          "pattern": "thank you",
          "text": "I understand, thank you!",
          "channel": "inc-21232-missing-data-in-identifierubimapping-tabl",
          "timestamp": "2026-04-07"
        },
        {
          "category": "Thanking",
          "pattern": "thank you",
          "text": "Thank you! One last thing for:\n\n&gt; essential, controller, ads prod will get to them soon.\nWhat did you mean? Did batch rebuild correctly overwrite",
          "channel": "inc-21232-missing-data-in-identifierubimapping-tabl",
          "timestamp": "2026-04-07"
        },
        {
          "category": "Thanking",
          "pattern": "thanks!",
          "text": "Thanks! Did you also make the Tech design google doc we could all contribute to? I could add our notes on inference and close the issue.",
          "channel": "proj-data-platform-cookie-identity-resolution",
          "timestamp": "2026-04-07"
        },
        {
          "category": "Thanking",
          "pattern": "thank you",
          "text": "No worries, seems a very straightforward change. And I have your PR as an example, thank you so much!",
          "channel": "identity-graph-data-atc",
          "timestamp": "2026-04-03"
        },
        {
          "category": "Thanking",
          "pattern": "thank you",
          "text": "Thank you! Sorry for all the questions on a holiday. Please return eating chocolate and chase bunnies.",
          "channel": "identity-graph-data-atc",
          "timestamp": "2026-04-03"
        },
        {
          "category": "Celebrating",
          "pattern": "amazing",
          "text": "Amazing!! Great improvement :slightly_smiling_face:",
          "channel": "proj-data-platform-cookie-identity-resolution",
          "timestamp": "2026-03-26"
        },
        {
          "category": "Thanking",
          "pattern": "thanks!",
          "text": "Definitely prefer the 24h window, great news thanks!",
          "channel": "proj-data-platform-cookie-identity-resolution",
          "timestamp": "2026-03-26"
        },
        {
          "category": "Acknowledging",
          "pattern": "i was wrong",
          "text": "Wow sorry. Looks like I was wrong again. So it\u2019s really about the size of the input data.",
          "channel": "identity-graph-data-atc",
          "timestamp": "2026-03-25"
        },
        {
          "category": "Acknowledging",
          "pattern": "i was wrong",
          "text": "I was wrong. Connections stats are lower.",
          "channel": "identity-graph-data-atc",
          "timestamp": "2026-03-25"
        },
        {
          "category": "Thanking",
          "pattern": "thanks!",
          "text": "Ok then let\u2019s keep creating them in cube-api-rs. Thanks!",
          "channel": "proj-data-platform-cookie-identity-resolution",
          "timestamp": "2026-03-16"
        }
      ],
      "negative_markers": [
        {
          "category": "Hostility",
          "pattern": "useless",
          "text": "No, it\u2019s just useless computations I believe. Also it prevents us from seeing the real violations across all tables. It\u2019s weird that means we don\u2019t",
          "channel": "identity-graph-data-atc",
          "timestamp": "2026-04-07"
        },
        {
          "category": "Dismissive",
          "pattern": "figure it out",
          "text": "I\u2019m investigating the SA permission, will do the revert if I can\u2019t figure it out",
          "channel": "identity-graph-data-atc",
          "timestamp": "2026-04-03"
        },
        {
          "category": "Hostility",
          "pattern": "stupid",
          "text": "Hey Zhen, I\u2019m asking a lot of stupid questions in the doc, sorry! For when you\u2019re back, could we do a meeting to go over this? I might just be",
          "channel": "proj-data-platform-cookie-identity-resolution",
          "timestamp": "2026-04-02"
        },
        {
          "category": "Dismissive",
          "pattern": "whatever",
          "text": "The temp solution is to join less data. I could split it into two jobs with whatever needs to be joined before November 2025 vs after that requires",
          "channel": "identity-graph-data-atc",
          "timestamp": "2026-03-25"
        },
        {
          "category": "Hostility",
          "pattern": "stupid",
          "text": "I think the easiest fix for now is to focus on the ip_email_time job. It might just fail because of that stupid ip join to maxmind.",
          "channel": "identity-graph-data-atc",
          "timestamp": "2026-03-25"
        },
        {
          "category": "Dismissive",
          "pattern": "figure it out",
          "text": "It took me 10 min to figure it out lol, I clicked on so many queries in those logs",
          "channel": "identity-graph-data-atc",
          "timestamp": "2026-03-11"
        }
      ]
    },
    "outbound_mentions": {
      "score": 4.75,
      "count": 10,
      "top_mentioned": [
        {
          "user": "zhen.han",
          "count": 9
        },
        {
          "user": "timothy.truong",
          "count": 7
        },
        {
          "user": "harrison.lin",
          "count": 2
        },
        {
          "user": "connor.clark",
          "count": 2
        },
        {
          "user": "mahdi.sadjadi",
          "count": 2
        },
        {
          "user": "ali.mir",
          "count": 1
        },
        {
          "user": "jonny.lomond",
          "count": 1
        }
      ]
    },
    "channel_connections": {
      "score": 1.7,
      "count": 43,
      "top_channels": [
        {
          "channel": "identity-graph-data-atc",
          "messages": 136
        },
        {
          "channel": "proj-data-platform-cookie-identity-resolution",
          "messages": 59
        },
        {
          "channel": "inc-21232-missing-data-in-identifierubimapping-tabl",
          "messages": 30
        },
        {
          "channel": "event-refinery-dev-talk",
          "messages": 7
        },
        {
          "channel": "event-sweeper-dev",
          "messages": 4
        },
        {
          "channel": "identity-and-events-standup",
          "messages": 2
        },
        {
          "channel": "identity-graph",
          "messages": 1
        }
      ]
    },
    "inbound_mentions": {
      "score": 2.18,
      "count": 10,
      "top_mentioners": [
        {
          "user": "harrison.lin",
          "count": 3
        },
        {
          "user": "zhen.han",
          "count": 3
        },
        {
          "user": "jonny.lomond",
          "count": 1
        },
        {
          "user": "iurie.cangea",
          "count": 1
        },
        {
          "user": "ali.mir",
          "count": 1
        },
        {
          "user": "timothy.truong",
          "count": 1
        }
      ]
    }
  },
  "activity_patterns": {
    "by_hour": {
      "18": 34,
      "17": 17,
      "16": 30,
      "15": 15,
      "13": 40,
      "23": 3,
      "22": 36,
      "21": 14,
      "20": 19,
      "14": 10,
      "12": 5,
      "19": 14,
      "0": 2
    },
    "by_day": {
      "Wednesday": 82,
      "Tuesday": 87,
      "Friday": 48,
      "Thursday": 19,
      "Monday": 3
    }
  },
  "department_comparison": {
    "department": "Unknown",
    "user_score_30d": 4.95,
    "dept_average_30d": 4.74,
    "dept_rank": 575,
    "dept_size": 1663
  }
}