{
  "username": "kristofer.thorlaksson",
  "name": "Kristofer Thorlaksson",
  "generated_at": "2026-04-08T20:22:09.804447",
  "summary": {
    "message_count": 656,
    "channels_active": 15,
    "unique_people_mentioned": 21,
    "unique_mentioners": 14,
    "days_in_window": 21,
    "days_scale": 0.91
  },
  "categories": {
    "sentiment": {
      "score": 8.1,
      "pos_count": 31,
      "neg_count": 6,
      "positive_markers": [
        {
          "category": "Thanking",
          "pattern": "thank you",
          "text": "Sounds gooooood, thank you John!",
          "channel": "proj-rollouts-for-checkout-and-accounts-dev",
          "timestamp": "2026-04-08"
        },
        {
          "category": "Thanking",
          "pattern": "thank you",
          "text": "awesome, thank you Angelo :bufo-thanks:",
          "channel": "proj-rollouts-store-default-swaps",
          "timestamp": "2026-04-08"
        },
        {
          "category": "Thanking",
          "pattern": "thank you",
          "text": "sweet, thank you Iain!",
          "channel": "proj-rollouts-store-default-swaps",
          "timestamp": "2026-04-07"
        },
        {
          "category": "Offering Help",
          "pattern": "feel free to",
          "text": "Feel free to go and update it :bufo-thumbsup:",
          "channel": "proj-rollouts-for-checkout-and-accounts-dev",
          "timestamp": "2026-04-07"
        },
        {
          "category": "Offering Help",
          "pattern": "feel free to",
          "text": "Feel free to tell me \"don't bother with this right now\", or \"stop asking until the designs are ready\" :sweat_smile:",
          "channel": "proj-rollouts-for-checkout-and-accounts-dev",
          "timestamp": "2026-04-01"
        },
        {
          "category": "Thanking",
          "pattern": "thanks!",
          "text": "I'll let you get back to it, thanks!",
          "channel": "shop-bots",
          "timestamp": "2026-04-01"
        },
        {
          "category": "Thanking",
          "pattern": "thank you",
          "text": "Thank you Daniel!",
          "channel": "proj-rollouts-store-default-swaps",
          "timestamp": "2026-03-31"
        },
        {
          "category": "Offering Help",
          "pattern": "let me know if",
          "text": "let me know if there's anything I can add to my stack to make your work easier :bufo-thumbsup:",
          "channel": "proj-rollouts-for-checkout-and-accounts-dev",
          "timestamp": "2026-03-31"
        },
        {
          "category": "Thanking",
          "pattern": "thank you",
          "text": "awesome, thank you Daniel, super work right here :eevee_clap:\nI've gone ahead and stacked my work on top of yours :bufo-thumbsup:",
          "channel": "proj-rollouts-store-default-swaps",
          "timestamp": "2026-03-31"
        },
        {
          "category": "Thanking",
          "pattern": "thanks!",
          "text": "Ah ok, will do, thanks!",
          "channel": "proj-rollouts-for-checkout-and-accounts-dev",
          "timestamp": "2026-03-30"
        }
      ],
      "negative_markers": [
        {
          "category": "Dismissive",
          "pattern": "whatever",
          "text": "Well whatever, I'm going to do the restack first, then we'll see",
          "channel": "proj-rollouts-for-checkout-and-accounts-dev",
          "timestamp": "2026-04-08"
        },
        {
          "category": "Dismissive",
          "pattern": "whatever",
          "text": "Things will be missing, and UX may not be entirely finalized. I think it's totally fair to say we'll be ready with whatever UX we have by EOD",
          "channel": "proj-rollouts-for-checkout-and-accounts-dev",
          "timestamp": "2026-04-06"
        },
        {
          "category": "Dismissive",
          "pattern": "whatever",
          "text": "Once you give an extension like that to modify the content of a web page they can inject whatever they'd like ",
          "channel": "customizations-rnd",
          "timestamp": "2026-03-23"
        },
        {
          "category": "Dismissive",
          "pattern": "whatever",
          "text": "right now, in the legacy system, you can assign whatever color scheme you want to whichever surface you want",
          "channel": "proj-branding-api-refactor",
          "timestamp": "2026-03-20"
        },
        {
          "category": "Dismissive",
          "pattern": "whatever",
          "text": ":pikawave: Dropping into the thread from the PR Jamie linked to, but I have a question:\n\n> Updates to the old branding color schemes are sync'd as",
          "channel": "proj-branding-api-refactor",
          "timestamp": "2026-03-20"
        },
        {
          "category": "Dismissive",
          "pattern": "whatever",
          "text": "> We can\u2019t do the serialized response that customer accounts does\nYeah I figured, good to confirm though, thanks!\n\nJust want to make sure I",
          "channel": "proj-rollouts-for-checkout-and-accounts-dev",
          "timestamp": "2026-03-18"
        }
      ]
    },
    "outbound_mentions": {
      "score": 8.23,
      "count": 23,
      "top_mentioned": [
        {
          "user": "john.king",
          "count": 27
        },
        {
          "user": "greg.craft",
          "count": 26
        },
        {
          "user": "alyssa.wilkinson",
          "count": 14
        },
        {
          "user": "simon.bolduc",
          "count": 9
        },
        {
          "user": "alessandro.dalgrande",
          "count": 7
        },
        {
          "user": "stephen.selao",
          "count": 5
        },
        {
          "user": "jesse.hoffman",
          "count": 3
        },
        {
          "user": "jamie.guerrero",
          "count": 3
        },
        {
          "user": "thomas.marcucci",
          "count": 3
        },
        {
          "user": "daniel.podgornikabramovici",
          "count": 2
        }
      ]
    },
    "channel_connections": {
      "score": 7.75,
      "count": 253,
      "top_channels": [
        {
          "channel": "proj-rollouts-for-checkout-and-accounts-dev",
          "messages": 401
        },
        {
          "channel": "customizations-production-support",
          "messages": 55
        },
        {
          "channel": "proj-rollouts-store-default-swaps",
          "messages": 46
        },
        {
          "channel": "customizations-river",
          "messages": 36
        },
        {
          "channel": "customizations-rnd",
          "messages": 33
        },
        {
          "channel": "proj-branding-api-refactor",
          "messages": 27
        },
        {
          "channel": "pi",
          "messages": 18
        },
        {
          "channel": "proj-markets-checkouts-accounts-editor-dev",
          "messages": 13
        },
        {
          "channel": "developers-talk",
          "messages": 6
        },
        {
          "channel": "checkout-eng",
          "messages": 6
        }
      ]
    },
    "inbound_mentions": {
      "score": 8.43,
      "count": 52,
      "top_mentioners": [
        {
          "user": "simon.bolduc",
          "count": 19
        },
        {
          "user": "john.king",
          "count": 7
        },
        {
          "user": "jesse.hoffman",
          "count": 6
        },
        {
          "user": "kate.park",
          "count": 3
        },
        {
          "user": "greg.craft",
          "count": 3
        },
        {
          "user": "francis.pelland",
          "count": 2
        },
        {
          "user": "stephen.selao",
          "count": 2
        },
        {
          "user": "angelo.ocana",
          "count": 2
        },
        {
          "user": "alyssa.wilkinson",
          "count": 2
        },
        {
          "user": "rick.caplan",
          "count": 2
        }
      ]
    }
  },
  "activity_patterns": {
    "by_hour": {
      "18": 65,
      "17": 77,
      "16": 83,
      "15": 67,
      "14": 28,
      "13": 10,
      "0": 38,
      "23": 27,
      "20": 37,
      "19": 86,
      "1": 27,
      "21": 57,
      "22": 46,
      "3": 2,
      "2": 2,
      "12": 4
    },
    "by_day": {
      "Wednesday": 189,
      "Tuesday": 126,
      "Monday": 135,
      "Friday": 103,
      "Thursday": 103
    }
  },
  "department_comparison": {
    "department": "Unknown",
    "user_score_30d": 6.11,
    "dept_average_30d": 4.74,
    "dept_rank": 168,
    "dept_size": 1663
  }
}